login_if/__init__.py
login_if/checker.py
login_if-1.0.0.dist-info/METADATA
login_if-1.0.0.dist-info/WHEEL
login_if-1.0.0.dist-info/top_level.txt
login_if-1.0.0.dist-info/RECORD
