Metadata-Version: 2.4
Name: login-if
Version: 1.0.0
Summary: API key verification library for secure login checks
Author: OUBStudios
Requires-Python: >=3.6
Requires-Dist: requests
Dynamic: author
Dynamic: requires-dist
Dynamic: requires-python
Dynamic: summary
